{
    "fullName":"ArgRS vs GluRS pairwise comparison",
    "class":"Class I",
    "icon":"/fig/icon_white.png",
    "family1":"ArgRS",
    "family2":"GluRS",
    "fullName1":"Arginyl tRNA Synthetase",
    "fullName2":"Glutamyl tRNA Synthetase (discriminating)",
    "description":"Pairwise comparison of the Class I catalytic domains from the Arginyl tRNA Synthetase (ArgRS) and Glutamyl tRNA Synthetase (discriminating) (GluRS) families. \n\tMonomeric structures from the two families were aligned using 3DCOMB. The cross-family RMSD is the average RMSD between pairs of structures from different families, and is\n\t larger than the total RMSD, which compares structures both within- and between-families. ",
    "rmsd":    2.204,
    "rmsd1":    2.66,
    "rmsd2":    1.64,
    "crossFamilyRmsd":    3.07,
    "rmsdTotal":    2.75
}
