{
    "elements":[
"H1",
"L1",
"H2",
"L2",
"S1",
"L3",
"S2",
"L4",
"H3",
"L5",
"S3",
"L6",
"S4",
"L7",
"S5",
"L8",
"SH1"
    ],
    "accessions":[
"GlyT_Bact_5f5w_A_aeolicus.pdb",
"Gly_Bact_1ati_T_thermophilus.pdb",
"Glycyl.A.Candidatus_Thermoplasmatota.NC_002689.2.pdb",
"Glycyl.A.Crenarchaeota.NC_015518.1.pdb",
"Glycyl.A.Euryarchaeota.NC_015574.1.pdb",
"Glycyl.A.Thaumarchaeota.NC_018656.1.pdb",
"Glycyl.B.Actinobacteria.NC_015067.1.pdb",
"Glycyl.B.Deinococcus-Thermus.NC_006461.1.pdb",
"Glycyl.B.Spirochaetes.NC_002967.9.pdb",
"Glycyl.E.Apicomplexa.NC_036168.2.pdb",
"Glycyl.E.Ascomycota.NC_001134.8.pdb",
"Glycyl.E.Basidiomycota.NC_026485.1.pdb",
"Glycyl.E.Rhodophyta.NC_010129.1.pdb",
"Gly_Euk_2q5h_H_sapiens.pdb"
    ],
    "refSeq":"GlyT_Bact_5f5w_A_aeolicus.pdb",
    "median_H1.start":    237,
    "median_H1.end":    256,
    "GlyT_Bact_5f5w_A_aeolicus.pdb_H1.dlength":    0,
    "GlyT_Bact_5f5w_A_aeolicus.pdb_H1.length":    14,
    "Gly_Bact_1ati_T_thermophilus.pdb_H1.start":    237,
    "Gly_Bact_1ati_T_thermophilus.pdb_H1.end":    256,
    "Gly_Bact_1ati_T_thermophilus.pdb_H1.dlength":    6,
    "Gly_Bact_1ati_T_thermophilus.pdb_H1.length":    20,
    "Glycyl.A.Candidatus_Thermoplasmatota.NC_002689.2.pdb_H1.start":    237,
    "Glycyl.A.Candidatus_Thermoplasmatota.NC_002689.2.pdb_H1.end":    256,
    "Glycyl.A.Candidatus_Thermoplasmatota.NC_002689.2.pdb_H1.dlength":    5,
    "Glycyl.A.Candidatus_Thermoplasmatota.NC_002689.2.pdb_H1.length":    19,
    "Glycyl.A.Crenarchaeota.NC_015518.1.pdb_H1.start":    237,
    "Glycyl.A.Crenarchaeota.NC_015518.1.pdb_H1.end":    258,
    "Glycyl.A.Crenarchaeota.NC_015518.1.pdb_H1.dlength":    8,
    "Glycyl.A.Crenarchaeota.NC_015518.1.pdb_H1.length":    22,
    "Glycyl.A.Euryarchaeota.NC_015574.1.pdb_H1.start":    237,
    "Glycyl.A.Euryarchaeota.NC_015574.1.pdb_H1.end":    257,
    "Glycyl.A.Euryarchaeota.NC_015574.1.pdb_H1.dlength":    7,
    "Glycyl.A.Euryarchaeota.NC_015574.1.pdb_H1.length":    21,
    "Glycyl.A.Thaumarchaeota.NC_018656.1.pdb_H1.start":    237,
    "Glycyl.A.Thaumarchaeota.NC_018656.1.pdb_H1.end":    256,
    "Glycyl.A.Thaumarchaeota.NC_018656.1.pdb_H1.dlength":    6,
    "Glycyl.A.Thaumarchaeota.NC_018656.1.pdb_H1.length":    20,
    "Glycyl.B.Actinobacteria.NC_015067.1.pdb_H1.start":    237,
    "Glycyl.B.Actinobacteria.NC_015067.1.pdb_H1.end":    256,
    "Glycyl.B.Actinobacteria.NC_015067.1.pdb_H1.dlength":    6,
    "Glycyl.B.Actinobacteria.NC_015067.1.pdb_H1.length":    20,
    "Glycyl.B.Deinococcus-Thermus.NC_006461.1.pdb_H1.start":    237,
    "Glycyl.B.Deinococcus-Thermus.NC_006461.1.pdb_H1.end":    256,
    "Glycyl.B.Deinococcus-Thermus.NC_006461.1.pdb_H1.dlength":    6,
    "Glycyl.B.Deinococcus-Thermus.NC_006461.1.pdb_H1.length":    20,
    "Glycyl.B.Spirochaetes.NC_002967.9.pdb_H1.start":    237,
    "Glycyl.B.Spirochaetes.NC_002967.9.pdb_H1.end":    255,
    "Glycyl.B.Spirochaetes.NC_002967.9.pdb_H1.dlength":    5,
    "Glycyl.B.Spirochaetes.NC_002967.9.pdb_H1.length":    19,
    "Glycyl.E.Apicomplexa.NC_036168.2.pdb_H1.start":    237,
    "Glycyl.E.Apicomplexa.NC_036168.2.pdb_H1.end":    256,
    "Glycyl.E.Apicomplexa.NC_036168.2.pdb_H1.dlength":    6,
    "Glycyl.E.Apicomplexa.NC_036168.2.pdb_H1.length":    20,
    "Glycyl.E.Ascomycota.NC_001134.8.pdb_H1.start":    237,
    "Glycyl.E.Ascomycota.NC_001134.8.pdb_H1.end":    255,
    "Glycyl.E.Ascomycota.NC_001134.8.pdb_H1.dlength":    5,
    "Glycyl.E.Ascomycota.NC_001134.8.pdb_H1.length":    19,
    "Glycyl.E.Basidiomycota.NC_026485.1.pdb_H1.start":    237,
    "Glycyl.E.Basidiomycota.NC_026485.1.pdb_H1.end":    256,
    "Glycyl.E.Basidiomycota.NC_026485.1.pdb_H1.dlength":    6,
    "Glycyl.E.Basidiomycota.NC_026485.1.pdb_H1.length":    20,
    "Glycyl.E.Rhodophyta.NC_010129.1.pdb_H1.start":    237,
    "Glycyl.E.Rhodophyta.NC_010129.1.pdb_H1.end":    258,
    "Glycyl.E.Rhodophyta.NC_010129.1.pdb_H1.dlength":    8,
    "Glycyl.E.Rhodophyta.NC_010129.1.pdb_H1.length":    22,
    "Gly_Euk_2q5h_H_sapiens.pdb_H1.start":    237,
    "Gly_Euk_2q5h_H_sapiens.pdb_H1.end":    258,
    "Gly_Euk_2q5h_H_sapiens.pdb_H1.dlength":    8,
    "Gly_Euk_2q5h_H_sapiens.pdb_H1.length":    22,
    "H1.aln.start":    38,
    "H1.aln.end":    59,
    "median_L1.start":    257,
    "median_L1.end":    553,
    "GlyT_Bact_5f5w_A_aeolicus.pdb_L1.dlength":    0,
    "GlyT_Bact_5f5w_A_aeolicus.pdb_L1.length":    15,
    "Gly_Bact_1ati_T_thermophilus.pdb_L1.start":    257,
    "Gly_Bact_1ati_T_thermophilus.pdb_L1.end":    553,
    "Gly_Bact_1ati_T_thermophilus.pdb_L1.dlength":    51,
    "Gly_Bact_1ati_T_thermophilus.pdb_L1.length":    66,
    "Glycyl.A.Candidatus_Thermoplasmatota.NC_002689.2.pdb_L1.start":    257,
    "Glycyl.A.Candidatus_Thermoplasmatota.NC_002689.2.pdb_L1.end":    554,
    "Glycyl.A.Candidatus_Thermoplasmatota.NC_002689.2.pdb_L1.dlength":    89,
    "Glycyl.A.Candidatus_Thermoplasmatota.NC_002689.2.pdb_L1.length":    104,
    "Glycyl.A.Crenarchaeota.NC_015518.1.pdb_L1.start":    259,
    "Glycyl.A.Crenarchaeota.NC_015518.1.pdb_L1.end":    553,
    "Glycyl.A.Crenarchaeota.NC_015518.1.pdb_L1.dlength":    94,
    "Glycyl.A.Crenarchaeota.NC_015518.1.pdb_L1.length":    109,
    "Glycyl.A.Euryarchaeota.NC_015574.1.pdb_L1.start":    258,
    "Glycyl.A.Euryarchaeota.NC_015574.1.pdb_L1.end":    554,
    "Glycyl.A.Euryarchaeota.NC_015574.1.pdb_L1.dlength":    94,
    "Glycyl.A.Euryarchaeota.NC_015574.1.pdb_L1.length":    109,
    "Glycyl.A.Thaumarchaeota.NC_018656.1.pdb_L1.start":    257,
    "Glycyl.A.Thaumarchaeota.NC_018656.1.pdb_L1.end":    553,
    "Glycyl.A.Thaumarchaeota.NC_018656.1.pdb_L1.dlength":    94,
    "Glycyl.A.Thaumarchaeota.NC_018656.1.pdb_L1.length":    109,
    "Glycyl.B.Actinobacteria.NC_015067.1.pdb_L1.start":    257,
    "Glycyl.B.Actinobacteria.NC_015067.1.pdb_L1.end":    553,
    "Glycyl.B.Actinobacteria.NC_015067.1.pdb_L1.dlength":    93,
    "Glycyl.B.Actinobacteria.NC_015067.1.pdb_L1.length":    108,
    "Glycyl.B.Deinococcus-Thermus.NC_006461.1.pdb_L1.start":    257,
    "Glycyl.B.Deinococcus-Thermus.NC_006461.1.pdb_L1.end":    553,
    "Glycyl.B.Deinococcus-Thermus.NC_006461.1.pdb_L1.dlength":    119,
    "Glycyl.B.Deinococcus-Thermus.NC_006461.1.pdb_L1.length":    134,
    "Glycyl.B.Spirochaetes.NC_002967.9.pdb_L1.start":    256,
    "Glycyl.B.Spirochaetes.NC_002967.9.pdb_L1.end":    553,
    "Glycyl.B.Spirochaetes.NC_002967.9.pdb_L1.dlength":    80,
    "Glycyl.B.Spirochaetes.NC_002967.9.pdb_L1.length":    95,
    "Glycyl.E.Apicomplexa.NC_036168.2.pdb_L1.start":    257,
    "Glycyl.E.Apicomplexa.NC_036168.2.pdb_L1.end":    553,
    "Glycyl.E.Apicomplexa.NC_036168.2.pdb_L1.dlength":    157,
    "Glycyl.E.Apicomplexa.NC_036168.2.pdb_L1.length":    172,
    "Glycyl.E.Ascomycota.NC_001134.8.pdb_L1.start":    256,
    "Glycyl.E.Ascomycota.NC_001134.8.pdb_L1.end":    553,
    "Glycyl.E.Ascomycota.NC_001134.8.pdb_L1.dlength":    148,
    "Glycyl.E.Ascomycota.NC_001134.8.pdb_L1.length":    163,
    "Glycyl.E.Basidiomycota.NC_026485.1.pdb_L1.start":    257,
    "Glycyl.E.Basidiomycota.NC_026485.1.pdb_L1.end":    554,
    "Glycyl.E.Basidiomycota.NC_026485.1.pdb_L1.dlength":    151,
    "Glycyl.E.Basidiomycota.NC_026485.1.pdb_L1.length":    166,
    "Glycyl.E.Rhodophyta.NC_010129.1.pdb_L1.start":    259,
    "Glycyl.E.Rhodophyta.NC_010129.1.pdb_L1.end":    554,
    "Glycyl.E.Rhodophyta.NC_010129.1.pdb_L1.dlength":    119,
    "Glycyl.E.Rhodophyta.NC_010129.1.pdb_L1.length":    134,
    "Gly_Euk_2q5h_H_sapiens.pdb_L1.start":    259,
    "Gly_Euk_2q5h_H_sapiens.pdb_L1.end":    553,
    "Gly_Euk_2q5h_H_sapiens.pdb_L1.dlength":    112,
    "Gly_Euk_2q5h_H_sapiens.pdb_L1.length":    127,
    "L1.aln.start":    60,
    "L1.aln.end":    315,
    "median_H2.start":    554,
    "median_H2.end":    559,
    "GlyT_Bact_5f5w_A_aeolicus.pdb_H2.dlength":    0,
    "GlyT_Bact_5f5w_A_aeolicus.pdb_H2.length":    9,
    "Gly_Bact_1ati_T_thermophilus.pdb_H2.start":    554,
    "Gly_Bact_1ati_T_thermophilus.pdb_H2.end":    559,
    "Gly_Bact_1ati_T_thermophilus.pdb_H2.dlength":    -3,
    "Gly_Bact_1ati_T_thermophilus.pdb_H2.length":    6,
    "Glycyl.A.Candidatus_Thermoplasmatota.NC_002689.2.pdb_H2.start":    555,
    "Glycyl.A.Candidatus_Thermoplasmatota.NC_002689.2.pdb_H2.end":    559,
    "Glycyl.A.Candidatus_Thermoplasmatota.NC_002689.2.pdb_H2.dlength":    -4,
    "Glycyl.A.Candidatus_Thermoplasmatota.NC_002689.2.pdb_H2.length":    5,
    "Glycyl.A.Crenarchaeota.NC_015518.1.pdb_H2.start":    554,
    "Glycyl.A.Crenarchaeota.NC_015518.1.pdb_H2.end":    567,
    "Glycyl.A.Crenarchaeota.NC_015518.1.pdb_H2.dlength":    5,
    "Glycyl.A.Crenarchaeota.NC_015518.1.pdb_H2.length":    14,
    "Glycyl.A.Euryarchaeota.NC_015574.1.pdb_H2.start":    555,
    "Glycyl.A.Euryarchaeota.NC_015574.1.pdb_H2.end":    558,
    "Glycyl.A.Euryarchaeota.NC_015574.1.pdb_H2.dlength":    -5,
    "Glycyl.A.Euryarchaeota.NC_015574.1.pdb_H2.length":    4,
    "Glycyl.A.Thaumarchaeota.NC_018656.1.pdb_H2.start":    554,
    "Glycyl.A.Thaumarchaeota.NC_018656.1.pdb_H2.end":    567,
    "Glycyl.A.Thaumarchaeota.NC_018656.1.pdb_H2.dlength":    5,
    "Glycyl.A.Thaumarchaeota.NC_018656.1.pdb_H2.length":    14,
    "Glycyl.B.Actinobacteria.NC_015067.1.pdb_H2.start":    554,
    "Glycyl.B.Actinobacteria.NC_015067.1.pdb_H2.end":    568,
    "Glycyl.B.Actinobacteria.NC_015067.1.pdb_H2.dlength":    6,
    "Glycyl.B.Actinobacteria.NC_015067.1.pdb_H2.length":    15,
    "Glycyl.B.Deinococcus-Thermus.NC_006461.1.pdb_H2.start":    554,
    "Glycyl.B.Deinococcus-Thermus.NC_006461.1.pdb_H2.end":    568,
    "Glycyl.B.Deinococcus-Thermus.NC_006461.1.pdb_H2.dlength":    6,
    "Glycyl.B.Deinococcus-Thermus.NC_006461.1.pdb_H2.length":    15,
    "Glycyl.B.Spirochaetes.NC_002967.9.pdb_H2.start":    554,
    "Glycyl.B.Spirochaetes.NC_002967.9.pdb_H2.end":    568,
    "Glycyl.B.Spirochaetes.NC_002967.9.pdb_H2.dlength":    6,
    "Glycyl.B.Spirochaetes.NC_002967.9.pdb_H2.length":    15,
    "Glycyl.E.Apicomplexa.NC_036168.2.pdb_H2.start":    554,
    "Glycyl.E.Apicomplexa.NC_036168.2.pdb_H2.end":    559,
    "Glycyl.E.Apicomplexa.NC_036168.2.pdb_H2.dlength":    -3,
    "Glycyl.E.Apicomplexa.NC_036168.2.pdb_H2.length":    6,
    "Glycyl.E.Ascomycota.NC_001134.8.pdb_H2.start":    554,
    "Glycyl.E.Ascomycota.NC_001134.8.pdb_H2.end":    559,
    "Glycyl.E.Ascomycota.NC_001134.8.pdb_H2.dlength":    -3,
    "Glycyl.E.Ascomycota.NC_001134.8.pdb_H2.length":    6,
    "Glycyl.E.Basidiomycota.NC_026485.1.pdb_H2.start":    555,
    "Glycyl.E.Basidiomycota.NC_026485.1.pdb_H2.end":    559,
    "Glycyl.E.Basidiomycota.NC_026485.1.pdb_H2.dlength":    -4,
    "Glycyl.E.Basidiomycota.NC_026485.1.pdb_H2.length":    5,
    "Glycyl.E.Rhodophyta.NC_010129.1.pdb_H2.start":    555,
    "Glycyl.E.Rhodophyta.NC_010129.1.pdb_H2.end":    559,
    "Glycyl.E.Rhodophyta.NC_010129.1.pdb_H2.dlength":    -4,
    "Glycyl.E.Rhodophyta.NC_010129.1.pdb_H2.length":    5,
    "Gly_Euk_2q5h_H_sapiens.pdb_H2.start":    554,
    "Gly_Euk_2q5h_H_sapiens.pdb_H2.end":    559,
    "Gly_Euk_2q5h_H_sapiens.pdb_H2.dlength":    -3,
    "Gly_Euk_2q5h_H_sapiens.pdb_H2.length":    6,
    "H2.aln.start":    316,
    "H2.aln.end":    323,
    "median_L2.start":    560,
    "median_L2.end":    573,
    "GlyT_Bact_5f5w_A_aeolicus.pdb_L2.dlength":    0,
    "GlyT_Bact_5f5w_A_aeolicus.pdb_L2.length":    7,
    "Gly_Bact_1ati_T_thermophilus.pdb_L2.start":    560,
    "Gly_Bact_1ati_T_thermophilus.pdb_L2.end":    573,
    "Gly_Bact_1ati_T_thermophilus.pdb_L2.dlength":    7,
    "Gly_Bact_1ati_T_thermophilus.pdb_L2.length":    14,
    "Glycyl.A.Candidatus_Thermoplasmatota.NC_002689.2.pdb_L2.start":    560,
    "Glycyl.A.Candidatus_Thermoplasmatota.NC_002689.2.pdb_L2.end":    573,
    "Glycyl.A.Candidatus_Thermoplasmatota.NC_002689.2.pdb_L2.dlength":    7,
    "Glycyl.A.Candidatus_Thermoplasmatota.NC_002689.2.pdb_L2.length":    14,
    "Glycyl.A.Crenarchaeota.NC_015518.1.pdb_L2.start":    568,
    "Glycyl.A.Crenarchaeota.NC_015518.1.pdb_L2.end":    573,
    "Glycyl.A.Crenarchaeota.NC_015518.1.pdb_L2.dlength":    -1,
    "Glycyl.A.Crenarchaeota.NC_015518.1.pdb_L2.length":    6,
    "Glycyl.A.Euryarchaeota.NC_015574.1.pdb_L2.start":    559,
    "Glycyl.A.Euryarchaeota.NC_015574.1.pdb_L2.end":    573,
    "Glycyl.A.Euryarchaeota.NC_015574.1.pdb_L2.dlength":    8,
    "Glycyl.A.Euryarchaeota.NC_015574.1.pdb_L2.length":    15,
    "Glycyl.A.Thaumarchaeota.NC_018656.1.pdb_L2.start":    568,
    "Glycyl.A.Thaumarchaeota.NC_018656.1.pdb_L2.end":    573,
    "Glycyl.A.Thaumarchaeota.NC_018656.1.pdb_L2.dlength":    -1,
    "Glycyl.A.Thaumarchaeota.NC_018656.1.pdb_L2.length":    6,
    "Glycyl.B.Actinobacteria.NC_015067.1.pdb_L2.start":    569,
    "Glycyl.B.Actinobacteria.NC_015067.1.pdb_L2.end":    573,
    "Glycyl.B.Actinobacteria.NC_015067.1.pdb_L2.dlength":    -2,
    "Glycyl.B.Actinobacteria.NC_015067.1.pdb_L2.length":    5,
    "Glycyl.B.Deinococcus-Thermus.NC_006461.1.pdb_L2.start":    569,
    "Glycyl.B.Deinococcus-Thermus.NC_006461.1.pdb_L2.end":    573,
    "Glycyl.B.Deinococcus-Thermus.NC_006461.1.pdb_L2.dlength":    -2,
    "Glycyl.B.Deinococcus-Thermus.NC_006461.1.pdb_L2.length":    5,
    "Glycyl.B.Spirochaetes.NC_002967.9.pdb_L2.start":    569,
    "Glycyl.B.Spirochaetes.NC_002967.9.pdb_L2.end":    573,
    "Glycyl.B.Spirochaetes.NC_002967.9.pdb_L2.dlength":    -2,
    "Glycyl.B.Spirochaetes.NC_002967.9.pdb_L2.length":    5,
    "Glycyl.E.Apicomplexa.NC_036168.2.pdb_L2.start":    560,
    "Glycyl.E.Apicomplexa.NC_036168.2.pdb_L2.end":    573,
    "Glycyl.E.Apicomplexa.NC_036168.2.pdb_L2.dlength":    7,
    "Glycyl.E.Apicomplexa.NC_036168.2.pdb_L2.length":    14,
    "Glycyl.E.Ascomycota.NC_001134.8.pdb_L2.start":    560,
    "Glycyl.E.Ascomycota.NC_001134.8.pdb_L2.end":    573,
    "Glycyl.E.Ascomycota.NC_001134.8.pdb_L2.dlength":    7,
    "Glycyl.E.Ascomycota.NC_001134.8.pdb_L2.length":    14,
    "Glycyl.E.Basidiomycota.NC_026485.1.pdb_L2.start":    560,
    "Glycyl.E.Basidiomycota.NC_026485.1.pdb_L2.end":    573,
    "Glycyl.E.Basidiomycota.NC_026485.1.pdb_L2.dlength":    7,
    "Glycyl.E.Basidiomycota.NC_026485.1.pdb_L2.length":    14,
    "Glycyl.E.Rhodophyta.NC_010129.1.pdb_L2.start":    560,
    "Glycyl.E.Rhodophyta.NC_010129.1.pdb_L2.end":    573,
    "Glycyl.E.Rhodophyta.NC_010129.1.pdb_L2.dlength":    7,
    "Glycyl.E.Rhodophyta.NC_010129.1.pdb_L2.length":    14,
    "Gly_Euk_2q5h_H_sapiens.pdb_L2.start":    560,
    "Gly_Euk_2q5h_H_sapiens.pdb_L2.end":    573,
    "Gly_Euk_2q5h_H_sapiens.pdb_L2.dlength":    7,
    "Gly_Euk_2q5h_H_sapiens.pdb_L2.length":    14,
    "L2.aln.start":    324,
    "L2.aln.end":    337,
    "median_S1.start":    574,
    "median_S1.end":    583,
    "GlyT_Bact_5f5w_A_aeolicus.pdb_S1.dlength":    0,
    "GlyT_Bact_5f5w_A_aeolicus.pdb_S1.length":    10,
    "Gly_Bact_1ati_T_thermophilus.pdb_S1.start":    574,
    "Gly_Bact_1ati_T_thermophilus.pdb_S1.end":    583,
    "Gly_Bact_1ati_T_thermophilus.pdb_S1.dlength":    0,
    "Gly_Bact_1ati_T_thermophilus.pdb_S1.length":    10,
    "Glycyl.A.Candidatus_Thermoplasmatota.NC_002689.2.pdb_S1.start":    574,
    "Glycyl.A.Candidatus_Thermoplasmatota.NC_002689.2.pdb_S1.end":    583,
    "Glycyl.A.Candidatus_Thermoplasmatota.NC_002689.2.pdb_S1.dlength":    0,
    "Glycyl.A.Candidatus_Thermoplasmatota.NC_002689.2.pdb_S1.length":    10,
    "Glycyl.A.Crenarchaeota.NC_015518.1.pdb_S1.start":    574,
    "Glycyl.A.Crenarchaeota.NC_015518.1.pdb_S1.end":    583,
    "Glycyl.A.Crenarchaeota.NC_015518.1.pdb_S1.dlength":    0,
    "Glycyl.A.Crenarchaeota.NC_015518.1.pdb_S1.length":    10,
    "Glycyl.A.Euryarchaeota.NC_015574.1.pdb_S1.start":    574,
    "Glycyl.A.Euryarchaeota.NC_015574.1.pdb_S1.end":    583,
    "Glycyl.A.Euryarchaeota.NC_015574.1.pdb_S1.dlength":    0,
    "Glycyl.A.Euryarchaeota.NC_015574.1.pdb_S1.length":    10,
    "Glycyl.A.Thaumarchaeota.NC_018656.1.pdb_S1.start":    574,
    "Glycyl.A.Thaumarchaeota.NC_018656.1.pdb_S1.end":    583,
    "Glycyl.A.Thaumarchaeota.NC_018656.1.pdb_S1.dlength":    0,
    "Glycyl.A.Thaumarchaeota.NC_018656.1.pdb_S1.length":    10,
    "Glycyl.B.Actinobacteria.NC_015067.1.pdb_S1.start":    574,
    "Glycyl.B.Actinobacteria.NC_015067.1.pdb_S1.end":    583,
    "Glycyl.B.Actinobacteria.NC_015067.1.pdb_S1.dlength":    0,
    "Glycyl.B.Actinobacteria.NC_015067.1.pdb_S1.length":    10,
    "Glycyl.B.Deinococcus-Thermus.NC_006461.1.pdb_S1.start":    574,
    "Glycyl.B.Deinococcus-Thermus.NC_006461.1.pdb_S1.end":    583,
    "Glycyl.B.Deinococcus-Thermus.NC_006461.1.pdb_S1.dlength":    0,
    "Glycyl.B.Deinococcus-Thermus.NC_006461.1.pdb_S1.length":    10,
    "Glycyl.B.Spirochaetes.NC_002967.9.pdb_S1.start":    574,
    "Glycyl.B.Spirochaetes.NC_002967.9.pdb_S1.end":    583,
    "Glycyl.B.Spirochaetes.NC_002967.9.pdb_S1.dlength":    0,
    "Glycyl.B.Spirochaetes.NC_002967.9.pdb_S1.length":    10,
    "Glycyl.E.Apicomplexa.NC_036168.2.pdb_S1.start":    574,
    "Glycyl.E.Apicomplexa.NC_036168.2.pdb_S1.end":    583,
    "Glycyl.E.Apicomplexa.NC_036168.2.pdb_S1.dlength":    0,
    "Glycyl.E.Apicomplexa.NC_036168.2.pdb_S1.length":    10,
    "Glycyl.E.Ascomycota.NC_001134.8.pdb_S1.start":    574,
    "Glycyl.E.Ascomycota.NC_001134.8.pdb_S1.end":    583,
    "Glycyl.E.Ascomycota.NC_001134.8.pdb_S1.dlength":    0,
    "Glycyl.E.Ascomycota.NC_001134.8.pdb_S1.length":    10,
    "Glycyl.E.Basidiomycota.NC_026485.1.pdb_S1.start":    574,
    "Glycyl.E.Basidiomycota.NC_026485.1.pdb_S1.end":    583,
    "Glycyl.E.Basidiomycota.NC_026485.1.pdb_S1.dlength":    0,
    "Glycyl.E.Basidiomycota.NC_026485.1.pdb_S1.length":    10,
    "Glycyl.E.Rhodophyta.NC_010129.1.pdb_S1.start":    574,
    "Glycyl.E.Rhodophyta.NC_010129.1.pdb_S1.end":    583,
    "Glycyl.E.Rhodophyta.NC_010129.1.pdb_S1.dlength":    0,
    "Glycyl.E.Rhodophyta.NC_010129.1.pdb_S1.length":    10,
    "Gly_Euk_2q5h_H_sapiens.pdb_S1.start":    574,
    "Gly_Euk_2q5h_H_sapiens.pdb_S1.end":    583,
    "Gly_Euk_2q5h_H_sapiens.pdb_S1.dlength":    0,
    "Gly_Euk_2q5h_H_sapiens.pdb_S1.length":    10,
    "S1.aln.start":    338,
    "S1.aln.end":    347,
    "median_L3.start":    584,
    "median_L3.end":    597,
    "GlyT_Bact_5f5w_A_aeolicus.pdb_L3.dlength":    0,
    "GlyT_Bact_5f5w_A_aeolicus.pdb_L3.length":    15,
    "Gly_Bact_1ati_T_thermophilus.pdb_L3.start":    584,
    "Gly_Bact_1ati_T_thermophilus.pdb_L3.end":    597,
    "Gly_Bact_1ati_T_thermophilus.pdb_L3.dlength":    -1,
    "Gly_Bact_1ati_T_thermophilus.pdb_L3.length":    14,
    "Glycyl.A.Candidatus_Thermoplasmatota.NC_002689.2.pdb_L3.start":    584,
    "Glycyl.A.Candidatus_Thermoplasmatota.NC_002689.2.pdb_L3.end":    597,
    "Glycyl.A.Candidatus_Thermoplasmatota.NC_002689.2.pdb_L3.dlength":    -1,
    "Glycyl.A.Candidatus_Thermoplasmatota.NC_002689.2.pdb_L3.length":    14,
    "Glycyl.A.Crenarchaeota.NC_015518.1.pdb_L3.start":    584,
    "Glycyl.A.Crenarchaeota.NC_015518.1.pdb_L3.end":    597,
    "Glycyl.A.Crenarchaeota.NC_015518.1.pdb_L3.dlength":    -1,
    "Glycyl.A.Crenarchaeota.NC_015518.1.pdb_L3.length":    14,
    "Glycyl.A.Euryarchaeota.NC_015574.1.pdb_L3.start":    584,
    "Glycyl.A.Euryarchaeota.NC_015574.1.pdb_L3.end":    597,
    "Glycyl.A.Euryarchaeota.NC_015574.1.pdb_L3.dlength":    -1,
    "Glycyl.A.Euryarchaeota.NC_015574.1.pdb_L3.length":    14,
    "Glycyl.A.Thaumarchaeota.NC_018656.1.pdb_L3.start":    584,
    "Glycyl.A.Thaumarchaeota.NC_018656.1.pdb_L3.end":    597,
    "Glycyl.A.Thaumarchaeota.NC_018656.1.pdb_L3.dlength":    -1,
    "Glycyl.A.Thaumarchaeota.NC_018656.1.pdb_L3.length":    14,
    "Glycyl.B.Actinobacteria.NC_015067.1.pdb_L3.start":    584,
    "Glycyl.B.Actinobacteria.NC_015067.1.pdb_L3.end":    597,
    "Glycyl.B.Actinobacteria.NC_015067.1.pdb_L3.dlength":    -1,
    "Glycyl.B.Actinobacteria.NC_015067.1.pdb_L3.length":    14,
    "Glycyl.B.Deinococcus-Thermus.NC_006461.1.pdb_L3.start":    584,
    "Glycyl.B.Deinococcus-Thermus.NC_006461.1.pdb_L3.end":    597,
    "Glycyl.B.Deinococcus-Thermus.NC_006461.1.pdb_L3.dlength":    -1,
    "Glycyl.B.Deinococcus-Thermus.NC_006461.1.pdb_L3.length":    14,
    "Glycyl.B.Spirochaetes.NC_002967.9.pdb_L3.start":    584,
    "Glycyl.B.Spirochaetes.NC_002967.9.pdb_L3.end":    597,
    "Glycyl.B.Spirochaetes.NC_002967.9.pdb_L3.dlength":    -1,
    "Glycyl.B.Spirochaetes.NC_002967.9.pdb_L3.length":    14,
    "Glycyl.E.Apicomplexa.NC_036168.2.pdb_L3.start":    584,
    "Glycyl.E.Apicomplexa.NC_036168.2.pdb_L3.end":    597,
    "Glycyl.E.Apicomplexa.NC_036168.2.pdb_L3.dlength":    -1,
    "Glycyl.E.Apicomplexa.NC_036168.2.pdb_L3.length":    14,
    "Glycyl.E.Ascomycota.NC_001134.8.pdb_L3.start":    584,
    "Glycyl.E.Ascomycota.NC_001134.8.pdb_L3.end":    597,
    "Glycyl.E.Ascomycota.NC_001134.8.pdb_L3.dlength":    -1,
    "Glycyl.E.Ascomycota.NC_001134.8.pdb_L3.length":    14,
    "Glycyl.E.Basidiomycota.NC_026485.1.pdb_L3.start":    584,
    "Glycyl.E.Basidiomycota.NC_026485.1.pdb_L3.end":    597,
    "Glycyl.E.Basidiomycota.NC_026485.1.pdb_L3.dlength":    -1,
    "Glycyl.E.Basidiomycota.NC_026485.1.pdb_L3.length":    14,
    "Glycyl.E.Rhodophyta.NC_010129.1.pdb_L3.start":    584,
    "Glycyl.E.Rhodophyta.NC_010129.1.pdb_L3.end":    597,
    "Glycyl.E.Rhodophyta.NC_010129.1.pdb_L3.dlength":    -1,
    "Glycyl.E.Rhodophyta.NC_010129.1.pdb_L3.length":    14,
    "Gly_Euk_2q5h_H_sapiens.pdb_L3.start":    584,
    "Gly_Euk_2q5h_H_sapiens.pdb_L3.end":    597,
    "Gly_Euk_2q5h_H_sapiens.pdb_L3.dlength":    -1,
    "Gly_Euk_2q5h_H_sapiens.pdb_L3.length":    14,
    "L3.aln.start":    348,
    "L3.aln.end":    363,
    "median_S2.start":    598,
    "median_S2.end":    608,
    "GlyT_Bact_5f5w_A_aeolicus.pdb_S2.dlength":    0,
    "GlyT_Bact_5f5w_A_aeolicus.pdb_S2.length":    10,
    "Gly_Bact_1ati_T_thermophilus.pdb_S2.start":    598,
    "Gly_Bact_1ati_T_thermophilus.pdb_S2.end":    608,
    "Gly_Bact_1ati_T_thermophilus.pdb_S2.dlength":    1,
    "Gly_Bact_1ati_T_thermophilus.pdb_S2.length":    11,
    "Glycyl.A.Candidatus_Thermoplasmatota.NC_002689.2.pdb_S2.start":    598,
    "Glycyl.A.Candidatus_Thermoplasmatota.NC_002689.2.pdb_S2.end":    608,
    "Glycyl.A.Candidatus_Thermoplasmatota.NC_002689.2.pdb_S2.dlength":    1,
    "Glycyl.A.Candidatus_Thermoplasmatota.NC_002689.2.pdb_S2.length":    11,
    "Glycyl.A.Crenarchaeota.NC_015518.1.pdb_S2.start":    598,
    "Glycyl.A.Crenarchaeota.NC_015518.1.pdb_S2.end":    608,
    "Glycyl.A.Crenarchaeota.NC_015518.1.pdb_S2.dlength":    1,
    "Glycyl.A.Crenarchaeota.NC_015518.1.pdb_S2.length":    11,
    "Glycyl.A.Euryarchaeota.NC_015574.1.pdb_S2.start":    598,
    "Glycyl.A.Euryarchaeota.NC_015574.1.pdb_S2.end":    608,
    "Glycyl.A.Euryarchaeota.NC_015574.1.pdb_S2.dlength":    1,
    "Glycyl.A.Euryarchaeota.NC_015574.1.pdb_S2.length":    11,
    "Glycyl.A.Thaumarchaeota.NC_018656.1.pdb_S2.start":    598,
    "Glycyl.A.Thaumarchaeota.NC_018656.1.pdb_S2.end":    608,
    "Glycyl.A.Thaumarchaeota.NC_018656.1.pdb_S2.dlength":    1,
    "Glycyl.A.Thaumarchaeota.NC_018656.1.pdb_S2.length":    11,
    "Glycyl.B.Actinobacteria.NC_015067.1.pdb_S2.start":    598,
    "Glycyl.B.Actinobacteria.NC_015067.1.pdb_S2.end":    608,
    "Glycyl.B.Actinobacteria.NC_015067.1.pdb_S2.dlength":    1,
    "Glycyl.B.Actinobacteria.NC_015067.1.pdb_S2.length":    11,
    "Glycyl.B.Deinococcus-Thermus.NC_006461.1.pdb_S2.start":    598,
    "Glycyl.B.Deinococcus-Thermus.NC_006461.1.pdb_S2.end":    608,
    "Glycyl.B.Deinococcus-Thermus.NC_006461.1.pdb_S2.dlength":    1,
    "Glycyl.B.Deinococcus-Thermus.NC_006461.1.pdb_S2.length":    11,
    "Glycyl.B.Spirochaetes.NC_002967.9.pdb_S2.start":    598,
    "Glycyl.B.Spirochaetes.NC_002967.9.pdb_S2.end":    608,
    "Glycyl.B.Spirochaetes.NC_002967.9.pdb_S2.dlength":    1,
    "Glycyl.B.Spirochaetes.NC_002967.9.pdb_S2.length":    11,
    "Glycyl.E.Apicomplexa.NC_036168.2.pdb_S2.start":    598,
    "Glycyl.E.Apicomplexa.NC_036168.2.pdb_S2.end":    608,
    "Glycyl.E.Apicomplexa.NC_036168.2.pdb_S2.dlength":    1,
    "Glycyl.E.Apicomplexa.NC_036168.2.pdb_S2.length":    11,
    "Glycyl.E.Ascomycota.NC_001134.8.pdb_S2.start":    598,
    "Glycyl.E.Ascomycota.NC_001134.8.pdb_S2.end":    608,
    "Glycyl.E.Ascomycota.NC_001134.8.pdb_S2.dlength":    1,
    "Glycyl.E.Ascomycota.NC_001134.8.pdb_S2.length":    11,
    "Glycyl.E.Basidiomycota.NC_026485.1.pdb_S2.start":    598,
    "Glycyl.E.Basidiomycota.NC_026485.1.pdb_S2.end":    608,
    "Glycyl.E.Basidiomycota.NC_026485.1.pdb_S2.dlength":    1,
    "Glycyl.E.Basidiomycota.NC_026485.1.pdb_S2.length":    11,
    "Glycyl.E.Rhodophyta.NC_010129.1.pdb_S2.start":    598,
    "Glycyl.E.Rhodophyta.NC_010129.1.pdb_S2.end":    608,
    "Glycyl.E.Rhodophyta.NC_010129.1.pdb_S2.dlength":    1,
    "Glycyl.E.Rhodophyta.NC_010129.1.pdb_S2.length":    11,
    "Gly_Euk_2q5h_H_sapiens.pdb_S2.start":    598,
    "Gly_Euk_2q5h_H_sapiens.pdb_S2.end":    608,
    "Gly_Euk_2q5h_H_sapiens.pdb_S2.dlength":    1,
    "Gly_Euk_2q5h_H_sapiens.pdb_S2.length":    11,
    "S2.aln.start":    364,
    "S2.aln.end":    374,
    "median_L4.start":    609,
    "median_L4.end":    665,
    "GlyT_Bact_5f5w_A_aeolicus.pdb_L4.dlength":    0,
    "GlyT_Bact_5f5w_A_aeolicus.pdb_L4.length":    5,
    "Gly_Bact_1ati_T_thermophilus.pdb_L4.start":    609,
    "Gly_Bact_1ati_T_thermophilus.pdb_L4.end":    609,
    "Gly_Bact_1ati_T_thermophilus.pdb_L4.dlength":    -4,
    "Gly_Bact_1ati_T_thermophilus.pdb_L4.length":    1,
    "Glycyl.A.Candidatus_Thermoplasmatota.NC_002689.2.pdb_L4.start":    609,
    "Glycyl.A.Candidatus_Thermoplasmatota.NC_002689.2.pdb_L4.end":    665,
    "Glycyl.A.Candidatus_Thermoplasmatota.NC_002689.2.pdb_L4.dlength":    35,
    "Glycyl.A.Candidatus_Thermoplasmatota.NC_002689.2.pdb_L4.length":    40,
    "Glycyl.A.Crenarchaeota.NC_015518.1.pdb_L4.start":    609,
    "Glycyl.A.Crenarchaeota.NC_015518.1.pdb_L4.end":    665,
    "Glycyl.A.Crenarchaeota.NC_015518.1.pdb_L4.dlength":    43,
    "Glycyl.A.Crenarchaeota.NC_015518.1.pdb_L4.length":    48,
    "Glycyl.A.Euryarchaeota.NC_015574.1.pdb_L4.start":    609,
    "Glycyl.A.Euryarchaeota.NC_015574.1.pdb_L4.end":    665,
    "Glycyl.A.Euryarchaeota.NC_015574.1.pdb_L4.dlength":    43,
    "Glycyl.A.Euryarchaeota.NC_015574.1.pdb_L4.length":    48,
    "Glycyl.A.Thaumarchaeota.NC_018656.1.pdb_L4.start":    609,
    "Glycyl.A.Thaumarchaeota.NC_018656.1.pdb_L4.end":    665,
    "Glycyl.A.Thaumarchaeota.NC_018656.1.pdb_L4.dlength":    38,
    "Glycyl.A.Thaumarchaeota.NC_018656.1.pdb_L4.length":    43,
    "Glycyl.B.Actinobacteria.NC_015067.1.pdb_L4.start":    609,
    "Glycyl.B.Actinobacteria.NC_015067.1.pdb_L4.end":    612,
    "Glycyl.B.Actinobacteria.NC_015067.1.pdb_L4.dlength":    -1,
    "Glycyl.B.Actinobacteria.NC_015067.1.pdb_L4.length":    4,
    "Glycyl.B.Deinococcus-Thermus.NC_006461.1.pdb_L4.start":    609,
    "Glycyl.B.Deinococcus-Thermus.NC_006461.1.pdb_L4.end":    612,
    "Glycyl.B.Deinococcus-Thermus.NC_006461.1.pdb_L4.dlength":    -1,
    "Glycyl.B.Deinococcus-Thermus.NC_006461.1.pdb_L4.length":    4,
    "Glycyl.B.Spirochaetes.NC_002967.9.pdb_L4.start":    609,
    "Glycyl.B.Spirochaetes.NC_002967.9.pdb_L4.end":    612,
    "Glycyl.B.Spirochaetes.NC_002967.9.pdb_L4.dlength":    -1,
    "Glycyl.B.Spirochaetes.NC_002967.9.pdb_L4.length":    4,
    "Glycyl.E.Apicomplexa.NC_036168.2.pdb_L4.start":    609,
    "Glycyl.E.Apicomplexa.NC_036168.2.pdb_L4.end":    665,
    "Glycyl.E.Apicomplexa.NC_036168.2.pdb_L4.dlength":    45,
    "Glycyl.E.Apicomplexa.NC_036168.2.pdb_L4.length":    50,
    "Glycyl.E.Ascomycota.NC_001134.8.pdb_L4.start":    609,
    "Glycyl.E.Ascomycota.NC_001134.8.pdb_L4.end":    665,
    "Glycyl.E.Ascomycota.NC_001134.8.pdb_L4.dlength":    44,
    "Glycyl.E.Ascomycota.NC_001134.8.pdb_L4.length":    49,
    "Glycyl.E.Basidiomycota.NC_026485.1.pdb_L4.start":    609,
    "Glycyl.E.Basidiomycota.NC_026485.1.pdb_L4.end":    665,
    "Glycyl.E.Basidiomycota.NC_026485.1.pdb_L4.dlength":    44,
    "Glycyl.E.Basidiomycota.NC_026485.1.pdb_L4.length":    49,
    "Glycyl.E.Rhodophyta.NC_010129.1.pdb_L4.start":    609,
    "Glycyl.E.Rhodophyta.NC_010129.1.pdb_L4.end":    665,
    "Glycyl.E.Rhodophyta.NC_010129.1.pdb_L4.dlength":    48,
    "Glycyl.E.Rhodophyta.NC_010129.1.pdb_L4.length":    53,
    "Gly_Euk_2q5h_H_sapiens.pdb_L4.start":    609,
    "Gly_Euk_2q5h_H_sapiens.pdb_L4.end":    665,
    "Gly_Euk_2q5h_H_sapiens.pdb_L4.dlength":    43,
    "Gly_Euk_2q5h_H_sapiens.pdb_L4.length":    48,
    "L4.aln.start":    375,
    "L4.aln.end":    430,
    "median_H3.start":    666,
    "median_H3.end":    681,
    "GlyT_Bact_5f5w_A_aeolicus.pdb_H3.dlength":    0,
    "GlyT_Bact_5f5w_A_aeolicus.pdb_H3.length":    11,
    "Gly_Bact_1ati_T_thermophilus.pdb_H3.start":    610,
    "Gly_Bact_1ati_T_thermophilus.pdb_H3.end":    681,
    "Gly_Bact_1ati_T_thermophilus.pdb_H3.dlength":    10,
    "Gly_Bact_1ati_T_thermophilus.pdb_H3.length":    21,
    "Glycyl.A.Candidatus_Thermoplasmatota.NC_002689.2.pdb_H3.start":    666,
    "Glycyl.A.Candidatus_Thermoplasmatota.NC_002689.2.pdb_H3.end":    682,
    "Glycyl.A.Candidatus_Thermoplasmatota.NC_002689.2.pdb_H3.dlength":    6,
    "Glycyl.A.Candidatus_Thermoplasmatota.NC_002689.2.pdb_H3.length":    17,
    "Glycyl.A.Crenarchaeota.NC_015518.1.pdb_H3.start":    666,
    "Glycyl.A.Crenarchaeota.NC_015518.1.pdb_H3.end":    681,
    "Glycyl.A.Crenarchaeota.NC_015518.1.pdb_H3.dlength":    5,
    "Glycyl.A.Crenarchaeota.NC_015518.1.pdb_H3.length":    16,
    "Glycyl.A.Euryarchaeota.NC_015574.1.pdb_H3.start":    666,
    "Glycyl.A.Euryarchaeota.NC_015574.1.pdb_H3.end":    681,
    "Glycyl.A.Euryarchaeota.NC_015574.1.pdb_H3.dlength":    5,
    "Glycyl.A.Euryarchaeota.NC_015574.1.pdb_H3.length":    16,
    "Glycyl.A.Thaumarchaeota.NC_018656.1.pdb_H3.start":    666,
    "Glycyl.A.Thaumarchaeota.NC_018656.1.pdb_H3.end":    682,
    "Glycyl.A.Thaumarchaeota.NC_018656.1.pdb_H3.dlength":    6,
    "Glycyl.A.Thaumarchaeota.NC_018656.1.pdb_H3.length":    17,
    "Glycyl.B.Actinobacteria.NC_015067.1.pdb_H3.start":    613,
    "Glycyl.B.Actinobacteria.NC_015067.1.pdb_H3.end":    681,
    "Glycyl.B.Actinobacteria.NC_015067.1.pdb_H3.dlength":    7,
    "Glycyl.B.Actinobacteria.NC_015067.1.pdb_H3.length":    18,
    "Glycyl.B.Deinococcus-Thermus.NC_006461.1.pdb_H3.start":    613,
    "Glycyl.B.Deinococcus-Thermus.NC_006461.1.pdb_H3.end":    681,
    "Glycyl.B.Deinococcus-Thermus.NC_006461.1.pdb_H3.dlength":    7,
    "Glycyl.B.Deinococcus-Thermus.NC_006461.1.pdb_H3.length":    18,
    "Glycyl.B.Spirochaetes.NC_002967.9.pdb_H3.start":    613,
    "Glycyl.B.Spirochaetes.NC_002967.9.pdb_H3.end":    681,
    "Glycyl.B.Spirochaetes.NC_002967.9.pdb_H3.dlength":    7,
    "Glycyl.B.Spirochaetes.NC_002967.9.pdb_H3.length":    18,
    "Glycyl.E.Apicomplexa.NC_036168.2.pdb_H3.start":    666,
    "Glycyl.E.Apicomplexa.NC_036168.2.pdb_H3.end":    681,
    "Glycyl.E.Apicomplexa.NC_036168.2.pdb_H3.dlength":    5,
    "Glycyl.E.Apicomplexa.NC_036168.2.pdb_H3.length":    16,
    "Glycyl.E.Ascomycota.NC_001134.8.pdb_H3.start":    666,
    "Glycyl.E.Ascomycota.NC_001134.8.pdb_H3.end":    681,
    "Glycyl.E.Ascomycota.NC_001134.8.pdb_H3.dlength":    5,
    "Glycyl.E.Ascomycota.NC_001134.8.pdb_H3.length":    16,
    "Glycyl.E.Basidiomycota.NC_026485.1.pdb_H3.start":    666,
    "Glycyl.E.Basidiomycota.NC_026485.1.pdb_H3.end":    682,
    "Glycyl.E.Basidiomycota.NC_026485.1.pdb_H3.dlength":    6,
    "Glycyl.E.Basidiomycota.NC_026485.1.pdb_H3.length":    17,
    "Glycyl.E.Rhodophyta.NC_010129.1.pdb_H3.start":    666,
    "Glycyl.E.Rhodophyta.NC_010129.1.pdb_H3.end":    682,
    "Glycyl.E.Rhodophyta.NC_010129.1.pdb_H3.dlength":    6,
    "Glycyl.E.Rhodophyta.NC_010129.1.pdb_H3.length":    17,
    "Gly_Euk_2q5h_H_sapiens.pdb_H3.start":    666,
    "Gly_Euk_2q5h_H_sapiens.pdb_H3.end":    681,
    "Gly_Euk_2q5h_H_sapiens.pdb_H3.dlength":    5,
    "Gly_Euk_2q5h_H_sapiens.pdb_H3.length":    16,
    "H3.aln.start":    431,
    "H3.aln.end":    446,
    "median_L5.start":    682,
    "median_L5.end":    688,
    "GlyT_Bact_5f5w_A_aeolicus.pdb_L5.dlength":    0,
    "GlyT_Bact_5f5w_A_aeolicus.pdb_L5.length":    9,
    "Gly_Bact_1ati_T_thermophilus.pdb_L5.start":    682,
    "Gly_Bact_1ati_T_thermophilus.pdb_L5.end":    688,
    "Gly_Bact_1ati_T_thermophilus.pdb_L5.dlength":    -2,
    "Gly_Bact_1ati_T_thermophilus.pdb_L5.length":    7,
    "Glycyl.A.Candidatus_Thermoplasmatota.NC_002689.2.pdb_L5.start":    683,
    "Glycyl.A.Candidatus_Thermoplasmatota.NC_002689.2.pdb_L5.end":    688,
    "Glycyl.A.Candidatus_Thermoplasmatota.NC_002689.2.pdb_L5.dlength":    -3,
    "Glycyl.A.Candidatus_Thermoplasmatota.NC_002689.2.pdb_L5.length":    6,
    "Glycyl.A.Crenarchaeota.NC_015518.1.pdb_L5.start":    682,
    "Glycyl.A.Crenarchaeota.NC_015518.1.pdb_L5.end":    688,
    "Glycyl.A.Crenarchaeota.NC_015518.1.pdb_L5.dlength":    -2,
    "Glycyl.A.Crenarchaeota.NC_015518.1.pdb_L5.length":    7,
    "Glycyl.A.Euryarchaeota.NC_015574.1.pdb_L5.start":    682,
    "Glycyl.A.Euryarchaeota.NC_015574.1.pdb_L5.end":    688,
    "Glycyl.A.Euryarchaeota.NC_015574.1.pdb_L5.dlength":    -2,
    "Glycyl.A.Euryarchaeota.NC_015574.1.pdb_L5.length":    7,
    "Glycyl.A.Thaumarchaeota.NC_018656.1.pdb_L5.start":    683,
    "Glycyl.A.Thaumarchaeota.NC_018656.1.pdb_L5.end":    688,
    "Glycyl.A.Thaumarchaeota.NC_018656.1.pdb_L5.dlength":    -3,
    "Glycyl.A.Thaumarchaeota.NC_018656.1.pdb_L5.length":    6,
    "Glycyl.B.Actinobacteria.NC_015067.1.pdb_L5.start":    682,
    "Glycyl.B.Actinobacteria.NC_015067.1.pdb_L5.end":    688,
    "Glycyl.B.Actinobacteria.NC_015067.1.pdb_L5.dlength":    -2,
    "Glycyl.B.Actinobacteria.NC_015067.1.pdb_L5.length":    7,
    "Glycyl.B.Deinococcus-Thermus.NC_006461.1.pdb_L5.start":    682,
    "Glycyl.B.Deinococcus-Thermus.NC_006461.1.pdb_L5.end":    688,
    "Glycyl.B.Deinococcus-Thermus.NC_006461.1.pdb_L5.dlength":    -2,
    "Glycyl.B.Deinococcus-Thermus.NC_006461.1.pdb_L5.length":    7,
    "Glycyl.B.Spirochaetes.NC_002967.9.pdb_L5.start":    682,
    "Glycyl.B.Spirochaetes.NC_002967.9.pdb_L5.end":    688,
    "Glycyl.B.Spirochaetes.NC_002967.9.pdb_L5.dlength":    -2,
    "Glycyl.B.Spirochaetes.NC_002967.9.pdb_L5.length":    7,
    "Glycyl.E.Apicomplexa.NC_036168.2.pdb_L5.start":    682,
    "Glycyl.E.Apicomplexa.NC_036168.2.pdb_L5.end":    688,
    "Glycyl.E.Apicomplexa.NC_036168.2.pdb_L5.dlength":    -2,
    "Glycyl.E.Apicomplexa.NC_036168.2.pdb_L5.length":    7,
    "Glycyl.E.Ascomycota.NC_001134.8.pdb_L5.start":    682,
    "Glycyl.E.Ascomycota.NC_001134.8.pdb_L5.end":    702,
    "Glycyl.E.Ascomycota.NC_001134.8.pdb_L5.dlength":    12,
    "Glycyl.E.Ascomycota.NC_001134.8.pdb_L5.length":    21,
    "Glycyl.E.Basidiomycota.NC_026485.1.pdb_L5.start":    683,
    "Glycyl.E.Basidiomycota.NC_026485.1.pdb_L5.end":    688,
    "Glycyl.E.Basidiomycota.NC_026485.1.pdb_L5.dlength":    -3,
    "Glycyl.E.Basidiomycota.NC_026485.1.pdb_L5.length":    6,
    "Glycyl.E.Rhodophyta.NC_010129.1.pdb_L5.start":    683,
    "Glycyl.E.Rhodophyta.NC_010129.1.pdb_L5.end":    688,
    "Glycyl.E.Rhodophyta.NC_010129.1.pdb_L5.dlength":    -3,
    "Glycyl.E.Rhodophyta.NC_010129.1.pdb_L5.length":    6,
    "Gly_Euk_2q5h_H_sapiens.pdb_L5.start":    682,
    "Gly_Euk_2q5h_H_sapiens.pdb_L5.end":    688,
    "Gly_Euk_2q5h_H_sapiens.pdb_L5.dlength":    -2,
    "Gly_Euk_2q5h_H_sapiens.pdb_L5.length":    7,
    "L5.aln.start":    447,
    "L5.aln.end":    456,
    "median_S3.start":    689,
    "median_S3.end":    693,
    "GlyT_Bact_5f5w_A_aeolicus.pdb_S3.dlength":    0,
    "GlyT_Bact_5f5w_A_aeolicus.pdb_S3.length":    10,
    "Gly_Bact_1ati_T_thermophilus.pdb_S3.start":    689,
    "Gly_Bact_1ati_T_thermophilus.pdb_S3.end":    693,
    "Gly_Bact_1ati_T_thermophilus.pdb_S3.dlength":    -5,
    "Gly_Bact_1ati_T_thermophilus.pdb_S3.length":    5,
    "Glycyl.A.Candidatus_Thermoplasmatota.NC_002689.2.pdb_S3.start":    689,
    "Glycyl.A.Candidatus_Thermoplasmatota.NC_002689.2.pdb_S3.end":    693,
    "Glycyl.A.Candidatus_Thermoplasmatota.NC_002689.2.pdb_S3.dlength":    -5,
    "Glycyl.A.Candidatus_Thermoplasmatota.NC_002689.2.pdb_S3.length":    5,
    "Glycyl.A.Crenarchaeota.NC_015518.1.pdb_S3.start":    689,
    "Glycyl.A.Crenarchaeota.NC_015518.1.pdb_S3.end":    693,
    "Glycyl.A.Crenarchaeota.NC_015518.1.pdb_S3.dlength":    -5,
    "Glycyl.A.Crenarchaeota.NC_015518.1.pdb_S3.length":    5,
    "Glycyl.A.Euryarchaeota.NC_015574.1.pdb_S3.start":    689,
    "Glycyl.A.Euryarchaeota.NC_015574.1.pdb_S3.end":    693,
    "Glycyl.A.Euryarchaeota.NC_015574.1.pdb_S3.dlength":    -5,
    "Glycyl.A.Euryarchaeota.NC_015574.1.pdb_S3.length":    5,
    "Glycyl.A.Thaumarchaeota.NC_018656.1.pdb_S3.start":    689,
    "Glycyl.A.Thaumarchaeota.NC_018656.1.pdb_S3.end":    693,
    "Glycyl.A.Thaumarchaeota.NC_018656.1.pdb_S3.dlength":    -5,
    "Glycyl.A.Thaumarchaeota.NC_018656.1.pdb_S3.length":    5,
    "Glycyl.B.Actinobacteria.NC_015067.1.pdb_S3.start":    689,
    "Glycyl.B.Actinobacteria.NC_015067.1.pdb_S3.end":    693,
    "Glycyl.B.Actinobacteria.NC_015067.1.pdb_S3.dlength":    -5,
    "Glycyl.B.Actinobacteria.NC_015067.1.pdb_S3.length":    5,
    "Glycyl.B.Deinococcus-Thermus.NC_006461.1.pdb_S3.start":    689,
    "Glycyl.B.Deinococcus-Thermus.NC_006461.1.pdb_S3.end":    693,
    "Glycyl.B.Deinococcus-Thermus.NC_006461.1.pdb_S3.dlength":    -5,
    "Glycyl.B.Deinococcus-Thermus.NC_006461.1.pdb_S3.length":    5,
    "Glycyl.B.Spirochaetes.NC_002967.9.pdb_S3.start":    689,
    "Glycyl.B.Spirochaetes.NC_002967.9.pdb_S3.end":    693,
    "Glycyl.B.Spirochaetes.NC_002967.9.pdb_S3.dlength":    -5,
    "Glycyl.B.Spirochaetes.NC_002967.9.pdb_S3.length":    5,
    "Glycyl.E.Apicomplexa.NC_036168.2.pdb_S3.start":    689,
    "Glycyl.E.Apicomplexa.NC_036168.2.pdb_S3.end":    693,
    "Glycyl.E.Apicomplexa.NC_036168.2.pdb_S3.dlength":    -5,
    "Glycyl.E.Apicomplexa.NC_036168.2.pdb_S3.length":    5,
    "Glycyl.E.Ascomycota.NC_001134.8.pdb_S3.start":    703,
    "Glycyl.E.Ascomycota.NC_001134.8.pdb_S3.end":    713,
    "Glycyl.E.Ascomycota.NC_001134.8.pdb_S3.dlength":    1,
    "Glycyl.E.Ascomycota.NC_001134.8.pdb_S3.length":    11,
    "Glycyl.E.Basidiomycota.NC_026485.1.pdb_S3.start":    689,
    "Glycyl.E.Basidiomycota.NC_026485.1.pdb_S3.end":    693,
    "Glycyl.E.Basidiomycota.NC_026485.1.pdb_S3.dlength":    -5,
    "Glycyl.E.Basidiomycota.NC_026485.1.pdb_S3.length":    5,
    "Glycyl.E.Rhodophyta.NC_010129.1.pdb_S3.start":    689,
    "Glycyl.E.Rhodophyta.NC_010129.1.pdb_S3.end":    693,
    "Glycyl.E.Rhodophyta.NC_010129.1.pdb_S3.dlength":    -5,
    "Glycyl.E.Rhodophyta.NC_010129.1.pdb_S3.length":    5,
    "Gly_Euk_2q5h_H_sapiens.pdb_S3.start":    689,
    "Gly_Euk_2q5h_H_sapiens.pdb_S3.end":    693,
    "Gly_Euk_2q5h_H_sapiens.pdb_S3.dlength":    -5,
    "Gly_Euk_2q5h_H_sapiens.pdb_S3.length":    5,
    "S3.aln.start":    457,
    "S3.aln.end":    462,
    "median_L6.start":    694,
    "median_L6.end":    704,
    "GlyT_Bact_5f5w_A_aeolicus.pdb_L6.dlength":    0,
    "GlyT_Bact_5f5w_A_aeolicus.pdb_L6.length":    4,
    "Gly_Bact_1ati_T_thermophilus.pdb_L6.start":    694,
    "Gly_Bact_1ati_T_thermophilus.pdb_L6.end":    704,
    "Gly_Bact_1ati_T_thermophilus.pdb_L6.dlength":    7,
    "Gly_Bact_1ati_T_thermophilus.pdb_L6.length":    11,
    "Glycyl.A.Candidatus_Thermoplasmatota.NC_002689.2.pdb_L6.start":    694,
    "Glycyl.A.Candidatus_Thermoplasmatota.NC_002689.2.pdb_L6.end":    704,
    "Glycyl.A.Candidatus_Thermoplasmatota.NC_002689.2.pdb_L6.dlength":    7,
    "Glycyl.A.Candidatus_Thermoplasmatota.NC_002689.2.pdb_L6.length":    11,
    "Glycyl.A.Crenarchaeota.NC_015518.1.pdb_L6.start":    694,
    "Glycyl.A.Crenarchaeota.NC_015518.1.pdb_L6.end":    704,
    "Glycyl.A.Crenarchaeota.NC_015518.1.pdb_L6.dlength":    7,
    "Glycyl.A.Crenarchaeota.NC_015518.1.pdb_L6.length":    11,
    "Glycyl.A.Euryarchaeota.NC_015574.1.pdb_L6.start":    694,
    "Glycyl.A.Euryarchaeota.NC_015574.1.pdb_L6.end":    704,
    "Glycyl.A.Euryarchaeota.NC_015574.1.pdb_L6.dlength":    7,
    "Glycyl.A.Euryarchaeota.NC_015574.1.pdb_L6.length":    11,
    "Glycyl.A.Thaumarchaeota.NC_018656.1.pdb_L6.start":    694,
    "Glycyl.A.Thaumarchaeota.NC_018656.1.pdb_L6.end":    704,
    "Glycyl.A.Thaumarchaeota.NC_018656.1.pdb_L6.dlength":    7,
    "Glycyl.A.Thaumarchaeota.NC_018656.1.pdb_L6.length":    11,
    "Glycyl.B.Actinobacteria.NC_015067.1.pdb_L6.start":    694,
    "Glycyl.B.Actinobacteria.NC_015067.1.pdb_L6.end":    704,
    "Glycyl.B.Actinobacteria.NC_015067.1.pdb_L6.dlength":    7,
    "Glycyl.B.Actinobacteria.NC_015067.1.pdb_L6.length":    11,
    "Glycyl.B.Deinococcus-Thermus.NC_006461.1.pdb_L6.start":    694,
    "Glycyl.B.Deinococcus-Thermus.NC_006461.1.pdb_L6.end":    704,
    "Glycyl.B.Deinococcus-Thermus.NC_006461.1.pdb_L6.dlength":    7,
    "Glycyl.B.Deinococcus-Thermus.NC_006461.1.pdb_L6.length":    11,
    "Glycyl.B.Spirochaetes.NC_002967.9.pdb_L6.start":    694,
    "Glycyl.B.Spirochaetes.NC_002967.9.pdb_L6.end":    704,
    "Glycyl.B.Spirochaetes.NC_002967.9.pdb_L6.dlength":    7,
    "Glycyl.B.Spirochaetes.NC_002967.9.pdb_L6.length":    11,
    "Glycyl.E.Apicomplexa.NC_036168.2.pdb_L6.start":    694,
    "Glycyl.E.Apicomplexa.NC_036168.2.pdb_L6.end":    705,
    "Glycyl.E.Apicomplexa.NC_036168.2.pdb_L6.dlength":    8,
    "Glycyl.E.Apicomplexa.NC_036168.2.pdb_L6.length":    12,
    "Glycyl.E.Ascomycota.NC_001134.8.pdb_L6.start":    714,
    "Glycyl.E.Ascomycota.NC_001134.8.pdb_L6.end":    702,
    "Glycyl.E.Ascomycota.NC_001134.8.pdb_L6.dlength":    9,
    "Glycyl.E.Ascomycota.NC_001134.8.pdb_L6.length":    13,
    "Glycyl.E.Basidiomycota.NC_026485.1.pdb_L6.start":    694,
    "Glycyl.E.Basidiomycota.NC_026485.1.pdb_L6.end":    705,
    "Glycyl.E.Basidiomycota.NC_026485.1.pdb_L6.dlength":    8,
    "Glycyl.E.Basidiomycota.NC_026485.1.pdb_L6.length":    12,
    "Glycyl.E.Rhodophyta.NC_010129.1.pdb_L6.start":    694,
    "Glycyl.E.Rhodophyta.NC_010129.1.pdb_L6.end":    704,
    "Glycyl.E.Rhodophyta.NC_010129.1.pdb_L6.dlength":    7,
    "Glycyl.E.Rhodophyta.NC_010129.1.pdb_L6.length":    11,
    "Gly_Euk_2q5h_H_sapiens.pdb_L6.start":    694,
    "Gly_Euk_2q5h_H_sapiens.pdb_L6.end":    704,
    "Gly_Euk_2q5h_H_sapiens.pdb_L6.dlength":    5,
    "Gly_Euk_2q5h_H_sapiens.pdb_L6.length":    9,
    "L6.aln.start":    463,
    "L6.aln.end":    479,
    "median_S4.start":    705,
    "median_S4.end":    713,
    "GlyT_Bact_5f5w_A_aeolicus.pdb_S4.dlength":    0,
    "GlyT_Bact_5f5w_A_aeolicus.pdb_S4.length":    10,
    "Gly_Bact_1ati_T_thermophilus.pdb_S4.start":    705,
    "Gly_Bact_1ati_T_thermophilus.pdb_S4.end":    713,
    "Gly_Bact_1ati_T_thermophilus.pdb_S4.dlength":    -1,
    "Gly_Bact_1ati_T_thermophilus.pdb_S4.length":    9,
    "Glycyl.A.Candidatus_Thermoplasmatota.NC_002689.2.pdb_S4.start":    705,
    "Glycyl.A.Candidatus_Thermoplasmatota.NC_002689.2.pdb_S4.end":    713,
    "Glycyl.A.Candidatus_Thermoplasmatota.NC_002689.2.pdb_S4.dlength":    -1,
    "Glycyl.A.Candidatus_Thermoplasmatota.NC_002689.2.pdb_S4.length":    9,
    "Glycyl.A.Crenarchaeota.NC_015518.1.pdb_S4.start":    705,
    "Glycyl.A.Crenarchaeota.NC_015518.1.pdb_S4.end":    713,
    "Glycyl.A.Crenarchaeota.NC_015518.1.pdb_S4.dlength":    -1,
    "Glycyl.A.Crenarchaeota.NC_015518.1.pdb_S4.length":    9,
    "Glycyl.A.Euryarchaeota.NC_015574.1.pdb_S4.start":    705,
    "Glycyl.A.Euryarchaeota.NC_015574.1.pdb_S4.end":    713,
    "Glycyl.A.Euryarchaeota.NC_015574.1.pdb_S4.dlength":    -1,
    "Glycyl.A.Euryarchaeota.NC_015574.1.pdb_S4.length":    9,
    "Glycyl.A.Thaumarchaeota.NC_018656.1.pdb_S4.start":    705,
    "Glycyl.A.Thaumarchaeota.NC_018656.1.pdb_S4.end":    713,
    "Glycyl.A.Thaumarchaeota.NC_018656.1.pdb_S4.dlength":    -1,
    "Glycyl.A.Thaumarchaeota.NC_018656.1.pdb_S4.length":    9,
    "Glycyl.B.Actinobacteria.NC_015067.1.pdb_S4.start":    705,
    "Glycyl.B.Actinobacteria.NC_015067.1.pdb_S4.end":    712,
    "Glycyl.B.Actinobacteria.NC_015067.1.pdb_S4.dlength":    -2,
    "Glycyl.B.Actinobacteria.NC_015067.1.pdb_S4.length":    8,
    "Glycyl.B.Deinococcus-Thermus.NC_006461.1.pdb_S4.start":    705,
    "Glycyl.B.Deinococcus-Thermus.NC_006461.1.pdb_S4.end":    713,
    "Glycyl.B.Deinococcus-Thermus.NC_006461.1.pdb_S4.dlength":    -1,
    "Glycyl.B.Deinococcus-Thermus.NC_006461.1.pdb_S4.length":    9,
    "Glycyl.B.Spirochaetes.NC_002967.9.pdb_S4.start":    705,
    "Glycyl.B.Spirochaetes.NC_002967.9.pdb_S4.end":    713,
    "Glycyl.B.Spirochaetes.NC_002967.9.pdb_S4.dlength":    -1,
    "Glycyl.B.Spirochaetes.NC_002967.9.pdb_S4.length":    9,
    "Glycyl.E.Apicomplexa.NC_036168.2.pdb_S4.start":    706,
    "Glycyl.E.Apicomplexa.NC_036168.2.pdb_S4.end":    713,
    "Glycyl.E.Apicomplexa.NC_036168.2.pdb_S4.dlength":    -2,
    "Glycyl.E.Apicomplexa.NC_036168.2.pdb_S4.length":    8,
    "Glycyl.E.Ascomycota.NC_001134.8.pdb_S4.start":    703,
    "Glycyl.E.Ascomycota.NC_001134.8.pdb_S4.end":    713,
    "Glycyl.E.Ascomycota.NC_001134.8.pdb_S4.dlength":    1,
    "Glycyl.E.Ascomycota.NC_001134.8.pdb_S4.length":    11,
    "Glycyl.E.Basidiomycota.NC_026485.1.pdb_S4.start":    706,
    "Glycyl.E.Basidiomycota.NC_026485.1.pdb_S4.end":    713,
    "Glycyl.E.Basidiomycota.NC_026485.1.pdb_S4.dlength":    -2,
    "Glycyl.E.Basidiomycota.NC_026485.1.pdb_S4.length":    8,
    "Glycyl.E.Rhodophyta.NC_010129.1.pdb_S4.start":    705,
    "Glycyl.E.Rhodophyta.NC_010129.1.pdb_S4.end":    713,
    "Glycyl.E.Rhodophyta.NC_010129.1.pdb_S4.dlength":    -1,
    "Glycyl.E.Rhodophyta.NC_010129.1.pdb_S4.length":    9,
    "Gly_Euk_2q5h_H_sapiens.pdb_S4.start":    705,
    "Gly_Euk_2q5h_H_sapiens.pdb_S4.end":    713,
    "Gly_Euk_2q5h_H_sapiens.pdb_S4.dlength":    -1,
    "Gly_Euk_2q5h_H_sapiens.pdb_S4.length":    9,
    "S4.aln.start":    480,
    "S4.aln.end":    488,
    "median_L7.start":    714,
    "median_L7.end":    718,
    "GlyT_Bact_5f5w_A_aeolicus.pdb_L7.dlength":    0,
    "GlyT_Bact_5f5w_A_aeolicus.pdb_L7.length":    2,
    "Gly_Bact_1ati_T_thermophilus.pdb_L7.start":    714,
    "Gly_Bact_1ati_T_thermophilus.pdb_L7.end":    716,
    "Gly_Bact_1ati_T_thermophilus.pdb_L7.dlength":    0,
    "Gly_Bact_1ati_T_thermophilus.pdb_L7.length":    2,
    "Glycyl.A.Candidatus_Thermoplasmatota.NC_002689.2.pdb_L7.start":    714,
    "Glycyl.A.Candidatus_Thermoplasmatota.NC_002689.2.pdb_L7.end":    716,
    "Glycyl.A.Candidatus_Thermoplasmatota.NC_002689.2.pdb_L7.dlength":    0,
    "Glycyl.A.Candidatus_Thermoplasmatota.NC_002689.2.pdb_L7.length":    2,
    "Glycyl.A.Crenarchaeota.NC_015518.1.pdb_L7.start":    714,
    "Glycyl.A.Crenarchaeota.NC_015518.1.pdb_L7.end":    716,
    "Glycyl.A.Crenarchaeota.NC_015518.1.pdb_L7.dlength":    0,
    "Glycyl.A.Crenarchaeota.NC_015518.1.pdb_L7.length":    2,
    "Glycyl.A.Euryarchaeota.NC_015574.1.pdb_L7.start":    714,
    "Glycyl.A.Euryarchaeota.NC_015574.1.pdb_L7.end":    719,
    "Glycyl.A.Euryarchaeota.NC_015574.1.pdb_L7.dlength":    1,
    "Glycyl.A.Euryarchaeota.NC_015574.1.pdb_L7.length":    3,
    "Glycyl.A.Thaumarchaeota.NC_018656.1.pdb_L7.start":    714,
    "Glycyl.A.Thaumarchaeota.NC_018656.1.pdb_L7.end":    716,
    "Glycyl.A.Thaumarchaeota.NC_018656.1.pdb_L7.dlength":    0,
    "Glycyl.A.Thaumarchaeota.NC_018656.1.pdb_L7.length":    2,
    "Glycyl.B.Actinobacteria.NC_015067.1.pdb_L7.start":    713,
    "Glycyl.B.Actinobacteria.NC_015067.1.pdb_L7.end":    719,
    "Glycyl.B.Actinobacteria.NC_015067.1.pdb_L7.dlength":    5,
    "Glycyl.B.Actinobacteria.NC_015067.1.pdb_L7.length":    7,
    "Glycyl.B.Deinococcus-Thermus.NC_006461.1.pdb_L7.start":    714,
    "Glycyl.B.Deinococcus-Thermus.NC_006461.1.pdb_L7.end":    716,
    "Glycyl.B.Deinococcus-Thermus.NC_006461.1.pdb_L7.dlength":    0,
    "Glycyl.B.Deinococcus-Thermus.NC_006461.1.pdb_L7.length":    2,
    "Glycyl.B.Spirochaetes.NC_002967.9.pdb_L7.start":    714,
    "Glycyl.B.Spirochaetes.NC_002967.9.pdb_L7.end":    716,
    "Glycyl.B.Spirochaetes.NC_002967.9.pdb_L7.dlength":    0,
    "Glycyl.B.Spirochaetes.NC_002967.9.pdb_L7.length":    2,
    "Glycyl.E.Apicomplexa.NC_036168.2.pdb_L7.start":    714,
    "Glycyl.E.Apicomplexa.NC_036168.2.pdb_L7.end":    716,
    "Glycyl.E.Apicomplexa.NC_036168.2.pdb_L7.dlength":    0,
    "Glycyl.E.Apicomplexa.NC_036168.2.pdb_L7.length":    2,
    "Glycyl.E.Ascomycota.NC_001134.8.pdb_L7.start":    714,
    "Glycyl.E.Ascomycota.NC_001134.8.pdb_L7.end":    716,
    "Glycyl.E.Ascomycota.NC_001134.8.pdb_L7.dlength":    0,
    "Glycyl.E.Ascomycota.NC_001134.8.pdb_L7.length":    2,
    "Glycyl.E.Basidiomycota.NC_026485.1.pdb_L7.start":    714,
    "Glycyl.E.Basidiomycota.NC_026485.1.pdb_L7.end":    716,
    "Glycyl.E.Basidiomycota.NC_026485.1.pdb_L7.dlength":    0,
    "Glycyl.E.Basidiomycota.NC_026485.1.pdb_L7.length":    2,
    "Glycyl.E.Rhodophyta.NC_010129.1.pdb_L7.start":    714,
    "Glycyl.E.Rhodophyta.NC_010129.1.pdb_L7.end":    716,
    "Glycyl.E.Rhodophyta.NC_010129.1.pdb_L7.dlength":    0,
    "Glycyl.E.Rhodophyta.NC_010129.1.pdb_L7.length":    2,
    "Gly_Euk_2q5h_H_sapiens.pdb_L7.start":    714,
    "Gly_Euk_2q5h_H_sapiens.pdb_L7.end":    716,
    "Gly_Euk_2q5h_H_sapiens.pdb_L7.dlength":    0,
    "Gly_Euk_2q5h_H_sapiens.pdb_L7.length":    2,
    "L7.aln.start":    489,
    "L7.aln.end":    491,
    "median_S5.start":    719,
    "median_S5.end":    730,
    "GlyT_Bact_5f5w_A_aeolicus.pdb_S5.dlength":    0,
    "GlyT_Bact_5f5w_A_aeolicus.pdb_S5.length":    12,
    "Gly_Bact_1ati_T_thermophilus.pdb_S5.start":    719,
    "Gly_Bact_1ati_T_thermophilus.pdb_S5.end":    729,
    "Gly_Bact_1ati_T_thermophilus.pdb_S5.dlength":    -2,
    "Gly_Bact_1ati_T_thermophilus.pdb_S5.length":    10,
    "Glycyl.A.Candidatus_Thermoplasmatota.NC_002689.2.pdb_S5.start":    719,
    "Glycyl.A.Candidatus_Thermoplasmatota.NC_002689.2.pdb_S5.end":    731,
    "Glycyl.A.Candidatus_Thermoplasmatota.NC_002689.2.pdb_S5.dlength":    0,
    "Glycyl.A.Candidatus_Thermoplasmatota.NC_002689.2.pdb_S5.length":    12,
    "Glycyl.A.Crenarchaeota.NC_015518.1.pdb_S5.start":    719,
    "Glycyl.A.Crenarchaeota.NC_015518.1.pdb_S5.end":    731,
    "Glycyl.A.Crenarchaeota.NC_015518.1.pdb_S5.dlength":    0,
    "Glycyl.A.Crenarchaeota.NC_015518.1.pdb_S5.length":    12,
    "Glycyl.A.Euryarchaeota.NC_015574.1.pdb_S5.start":    720,
    "Glycyl.A.Euryarchaeota.NC_015574.1.pdb_S5.end":    729,
    "Glycyl.A.Euryarchaeota.NC_015574.1.pdb_S5.dlength":    -2,
    "Glycyl.A.Euryarchaeota.NC_015574.1.pdb_S5.length":    10,
    "Glycyl.A.Thaumarchaeota.NC_018656.1.pdb_S5.start":    719,
    "Glycyl.A.Thaumarchaeota.NC_018656.1.pdb_S5.end":    729,
    "Glycyl.A.Thaumarchaeota.NC_018656.1.pdb_S5.dlength":    -2,
    "Glycyl.A.Thaumarchaeota.NC_018656.1.pdb_S5.length":    10,
    "Glycyl.B.Actinobacteria.NC_015067.1.pdb_S5.start":    721,
    "Glycyl.B.Actinobacteria.NC_015067.1.pdb_S5.end":    731,
    "Glycyl.B.Actinobacteria.NC_015067.1.pdb_S5.dlength":    -1,
    "Glycyl.B.Actinobacteria.NC_015067.1.pdb_S5.length":    11,
    "Glycyl.B.Deinococcus-Thermus.NC_006461.1.pdb_S5.start":    719,
    "Glycyl.B.Deinococcus-Thermus.NC_006461.1.pdb_S5.end":    731,
    "Glycyl.B.Deinococcus-Thermus.NC_006461.1.pdb_S5.dlength":    0,
    "Glycyl.B.Deinococcus-Thermus.NC_006461.1.pdb_S5.length":    12,
    "Glycyl.B.Spirochaetes.NC_002967.9.pdb_S5.start":    719,
    "Glycyl.B.Spirochaetes.NC_002967.9.pdb_S5.end":    731,
    "Glycyl.B.Spirochaetes.NC_002967.9.pdb_S5.dlength":    0,
    "Glycyl.B.Spirochaetes.NC_002967.9.pdb_S5.length":    12,
    "Glycyl.E.Apicomplexa.NC_036168.2.pdb_S5.start":    719,
    "Glycyl.E.Apicomplexa.NC_036168.2.pdb_S5.end":    729,
    "Glycyl.E.Apicomplexa.NC_036168.2.pdb_S5.dlength":    -2,
    "Glycyl.E.Apicomplexa.NC_036168.2.pdb_S5.length":    10,
    "Glycyl.E.Ascomycota.NC_001134.8.pdb_S5.start":    719,
    "Glycyl.E.Ascomycota.NC_001134.8.pdb_S5.end":    731,
    "Glycyl.E.Ascomycota.NC_001134.8.pdb_S5.dlength":    0,
    "Glycyl.E.Ascomycota.NC_001134.8.pdb_S5.length":    12,
    "Glycyl.E.Basidiomycota.NC_026485.1.pdb_S5.start":    719,
    "Glycyl.E.Basidiomycota.NC_026485.1.pdb_S5.end":    729,
    "Glycyl.E.Basidiomycota.NC_026485.1.pdb_S5.dlength":    -2,
    "Glycyl.E.Basidiomycota.NC_026485.1.pdb_S5.length":    10,
    "Glycyl.E.Rhodophyta.NC_010129.1.pdb_S5.start":    719,
    "Glycyl.E.Rhodophyta.NC_010129.1.pdb_S5.end":    729,
    "Glycyl.E.Rhodophyta.NC_010129.1.pdb_S5.dlength":    -2,
    "Glycyl.E.Rhodophyta.NC_010129.1.pdb_S5.length":    10,
    "Gly_Euk_2q5h_H_sapiens.pdb_S5.start":    719,
    "Gly_Euk_2q5h_H_sapiens.pdb_S5.end":    730,
    "Gly_Euk_2q5h_H_sapiens.pdb_S5.dlength":    -1,
    "Gly_Euk_2q5h_H_sapiens.pdb_S5.length":    11,
    "S5.aln.start":    492,
    "S5.aln.end":    505,
    "median_L8.start":    731,
    "median_L8.end":    941,
    "GlyT_Bact_5f5w_A_aeolicus.pdb_L8.dlength":    0,
    "GlyT_Bact_5f5w_A_aeolicus.pdb_L8.length":    9,
    "Gly_Bact_1ati_T_thermophilus.pdb_L8.start":    730,
    "Gly_Bact_1ati_T_thermophilus.pdb_L8.end":    941,
    "Gly_Bact_1ati_T_thermophilus.pdb_L8.dlength":    36,
    "Gly_Bact_1ati_T_thermophilus.pdb_L8.length":    45,
    "Glycyl.A.Candidatus_Thermoplasmatota.NC_002689.2.pdb_L8.start":    732,
    "Glycyl.A.Candidatus_Thermoplasmatota.NC_002689.2.pdb_L8.end":    941,
    "Glycyl.A.Candidatus_Thermoplasmatota.NC_002689.2.pdb_L8.dlength":    13,
    "Glycyl.A.Candidatus_Thermoplasmatota.NC_002689.2.pdb_L8.length":    22,
    "Glycyl.A.Crenarchaeota.NC_015518.1.pdb_L8.start":    732,
    "Glycyl.A.Crenarchaeota.NC_015518.1.pdb_L8.end":    941,
    "Glycyl.A.Crenarchaeota.NC_015518.1.pdb_L8.dlength":    86,
    "Glycyl.A.Crenarchaeota.NC_015518.1.pdb_L8.length":    95,
    "Glycyl.A.Euryarchaeota.NC_015574.1.pdb_L8.start":    730,
    "Glycyl.A.Euryarchaeota.NC_015574.1.pdb_L8.end":    941,
    "Glycyl.A.Euryarchaeota.NC_015574.1.pdb_L8.dlength":    97,
    "Glycyl.A.Euryarchaeota.NC_015574.1.pdb_L8.length":    106,
    "Glycyl.A.Thaumarchaeota.NC_018656.1.pdb_L8.start":    730,
    "Glycyl.A.Thaumarchaeota.NC_018656.1.pdb_L8.end":    941,
    "Glycyl.A.Thaumarchaeota.NC_018656.1.pdb_L8.dlength":    19,
    "Glycyl.A.Thaumarchaeota.NC_018656.1.pdb_L8.length":    28,
    "Glycyl.B.Actinobacteria.NC_015067.1.pdb_L8.start":    732,
    "Glycyl.B.Actinobacteria.NC_015067.1.pdb_L8.end":    941,
    "Glycyl.B.Actinobacteria.NC_015067.1.pdb_L8.dlength":    19,
    "Glycyl.B.Actinobacteria.NC_015067.1.pdb_L8.length":    28,
    "Glycyl.B.Deinococcus-Thermus.NC_006461.1.pdb_L8.start":    732,
    "Glycyl.B.Deinococcus-Thermus.NC_006461.1.pdb_L8.end":    941,
    "Glycyl.B.Deinococcus-Thermus.NC_006461.1.pdb_L8.dlength":    34,
    "Glycyl.B.Deinococcus-Thermus.NC_006461.1.pdb_L8.length":    43,
    "Glycyl.B.Spirochaetes.NC_002967.9.pdb_L8.start":    732,
    "Glycyl.B.Spirochaetes.NC_002967.9.pdb_L8.end":    941,
    "Glycyl.B.Spirochaetes.NC_002967.9.pdb_L8.dlength":    20,
    "Glycyl.B.Spirochaetes.NC_002967.9.pdb_L8.length":    29,
    "Glycyl.E.Apicomplexa.NC_036168.2.pdb_L8.start":    730,
    "Glycyl.E.Apicomplexa.NC_036168.2.pdb_L8.end":    941,
    "Glycyl.E.Apicomplexa.NC_036168.2.pdb_L8.dlength":    108,
    "Glycyl.E.Apicomplexa.NC_036168.2.pdb_L8.length":    117,
    "Glycyl.E.Ascomycota.NC_001134.8.pdb_L8.start":    732,
    "Glycyl.E.Ascomycota.NC_001134.8.pdb_L8.end":    941,
    "Glycyl.E.Ascomycota.NC_001134.8.pdb_L8.dlength":    100,
    "Glycyl.E.Ascomycota.NC_001134.8.pdb_L8.length":    109,
    "Glycyl.E.Basidiomycota.NC_026485.1.pdb_L8.start":    730,
    "Glycyl.E.Basidiomycota.NC_026485.1.pdb_L8.end":    941,
    "Glycyl.E.Basidiomycota.NC_026485.1.pdb_L8.dlength":    100,
    "Glycyl.E.Basidiomycota.NC_026485.1.pdb_L8.length":    109,
    "Glycyl.E.Rhodophyta.NC_010129.1.pdb_L8.start":    730,
    "Glycyl.E.Rhodophyta.NC_010129.1.pdb_L8.end":    941,
    "Glycyl.E.Rhodophyta.NC_010129.1.pdb_L8.dlength":    96,
    "Glycyl.E.Rhodophyta.NC_010129.1.pdb_L8.length":    105,
    "Gly_Euk_2q5h_H_sapiens.pdb_L8.start":    731,
    "Gly_Euk_2q5h_H_sapiens.pdb_L8.end":    941,
    "Gly_Euk_2q5h_H_sapiens.pdb_L8.dlength":    19,
    "Gly_Euk_2q5h_H_sapiens.pdb_L8.length":    28,
    "L8.aln.start":    506,
    "L8.aln.end":    848,
    "median_SH1.start":    942,
    "median_SH1.end":    960,
    "GlyT_Bact_5f5w_A_aeolicus.pdb_SH1.dlength":    0,
    "GlyT_Bact_5f5w_A_aeolicus.pdb_SH1.length":    14,
    "Gly_Bact_1ati_T_thermophilus.pdb_SH1.start":    942,
    "Gly_Bact_1ati_T_thermophilus.pdb_SH1.end":    960,
    "Gly_Bact_1ati_T_thermophilus.pdb_SH1.dlength":    4,
    "Gly_Bact_1ati_T_thermophilus.pdb_SH1.length":    18,
    "Glycyl.A.Candidatus_Thermoplasmatota.NC_002689.2.pdb_SH1.start":    942,
    "Glycyl.A.Candidatus_Thermoplasmatota.NC_002689.2.pdb_SH1.end":    960,
    "Glycyl.A.Candidatus_Thermoplasmatota.NC_002689.2.pdb_SH1.dlength":    4,
    "Glycyl.A.Candidatus_Thermoplasmatota.NC_002689.2.pdb_SH1.length":    18,
    "Glycyl.A.Crenarchaeota.NC_015518.1.pdb_SH1.start":    942,
    "Glycyl.A.Crenarchaeota.NC_015518.1.pdb_SH1.end":    960,
    "Glycyl.A.Crenarchaeota.NC_015518.1.pdb_SH1.dlength":    4,
    "Glycyl.A.Crenarchaeota.NC_015518.1.pdb_SH1.length":    18,
    "Glycyl.A.Euryarchaeota.NC_015574.1.pdb_SH1.start":    942,
    "Glycyl.A.Euryarchaeota.NC_015574.1.pdb_SH1.end":    960,
    "Glycyl.A.Euryarchaeota.NC_015574.1.pdb_SH1.dlength":    4,
    "Glycyl.A.Euryarchaeota.NC_015574.1.pdb_SH1.length":    18,
    "Glycyl.A.Thaumarchaeota.NC_018656.1.pdb_SH1.start":    942,
    "Glycyl.A.Thaumarchaeota.NC_018656.1.pdb_SH1.end":    960,
    "Glycyl.A.Thaumarchaeota.NC_018656.1.pdb_SH1.dlength":    4,
    "Glycyl.A.Thaumarchaeota.NC_018656.1.pdb_SH1.length":    18,
    "Glycyl.B.Actinobacteria.NC_015067.1.pdb_SH1.start":    942,
    "Glycyl.B.Actinobacteria.NC_015067.1.pdb_SH1.end":    960,
    "Glycyl.B.Actinobacteria.NC_015067.1.pdb_SH1.dlength":    4,
    "Glycyl.B.Actinobacteria.NC_015067.1.pdb_SH1.length":    18,
    "Glycyl.B.Deinococcus-Thermus.NC_006461.1.pdb_SH1.start":    942,
    "Glycyl.B.Deinococcus-Thermus.NC_006461.1.pdb_SH1.end":    960,
    "Glycyl.B.Deinococcus-Thermus.NC_006461.1.pdb_SH1.dlength":    4,
    "Glycyl.B.Deinococcus-Thermus.NC_006461.1.pdb_SH1.length":    18,
    "Glycyl.B.Spirochaetes.NC_002967.9.pdb_SH1.start":    942,
    "Glycyl.B.Spirochaetes.NC_002967.9.pdb_SH1.end":    960,
    "Glycyl.B.Spirochaetes.NC_002967.9.pdb_SH1.dlength":    4,
    "Glycyl.B.Spirochaetes.NC_002967.9.pdb_SH1.length":    18,
    "Glycyl.E.Apicomplexa.NC_036168.2.pdb_SH1.start":    942,
    "Glycyl.E.Apicomplexa.NC_036168.2.pdb_SH1.end":    960,
    "Glycyl.E.Apicomplexa.NC_036168.2.pdb_SH1.dlength":    4,
    "Glycyl.E.Apicomplexa.NC_036168.2.pdb_SH1.length":    18,
    "Glycyl.E.Ascomycota.NC_001134.8.pdb_SH1.start":    942,
    "Glycyl.E.Ascomycota.NC_001134.8.pdb_SH1.end":    960,
    "Glycyl.E.Ascomycota.NC_001134.8.pdb_SH1.dlength":    4,
    "Glycyl.E.Ascomycota.NC_001134.8.pdb_SH1.length":    18,
    "Glycyl.E.Basidiomycota.NC_026485.1.pdb_SH1.start":    942,
    "Glycyl.E.Basidiomycota.NC_026485.1.pdb_SH1.end":    960,
    "Glycyl.E.Basidiomycota.NC_026485.1.pdb_SH1.dlength":    4,
    "Glycyl.E.Basidiomycota.NC_026485.1.pdb_SH1.length":    18,
    "Glycyl.E.Rhodophyta.NC_010129.1.pdb_SH1.start":    942,
    "Glycyl.E.Rhodophyta.NC_010129.1.pdb_SH1.end":    960,
    "Glycyl.E.Rhodophyta.NC_010129.1.pdb_SH1.dlength":    4,
    "Glycyl.E.Rhodophyta.NC_010129.1.pdb_SH1.length":    18,
    "Gly_Euk_2q5h_H_sapiens.pdb_SH1.start":    942,
    "Gly_Euk_2q5h_H_sapiens.pdb_SH1.end":    960,
    "Gly_Euk_2q5h_H_sapiens.pdb_SH1.dlength":    4,
    "Gly_Euk_2q5h_H_sapiens.pdb_SH1.length":    18,
    "SH1.aln.start":    849,
    "SH1.aln.end":    866
}
